COPYING.txt
MANIFEST.in
README.md
requirements.txt
setup.py
tox.ini
fretfinder/__init__.py
fretfinder/__main__.py
fretfinder/adaptive.py
fretfinder/algorithm.py
fretfinder/cursors.py
fretfinder/guitar.py
fretfinder/score.py
fretfinder.egg-info/PKG-INFO
fretfinder.egg-info/SOURCES.txt
fretfinder.egg-info/dependency_links.txt
fretfinder.egg-info/entry_points.txt
fretfinder.egg-info/requires.txt
fretfinder.egg-info/top_level.txt
test/__init__.py
test/test_adaptive.py